README.txt
control-server.example.yaml
credentials.yaml
deimos.yaml
minimal.example.yaml
node.example.yaml
phobos.yaml
runclaun.py
server.yaml
setup.py
claun/__init__.py
claun.egg-info/PKG-INFO
claun.egg-info/SOURCES.txt
claun.egg-info/dependency_links.txt
claun.egg-info/requires.txt
claun.egg-info/top_level.txt
claun/core/__init__.py
claun/core/configurator.py
claun/core/container.py
claun/core/log.py
claun/core/moduleloader.py
claun/core/communication/__init__.py
claun/core/communication/client/__init__.py
claun/core/communication/client/credentials_decorators.py
claun/core/communication/io/__init__.py
claun/core/communication/io/input.py
claun/core/communication/io/output.py
claun/core/communication/server/__init__.py
claun/core/communication/server/authenticators/__init__.py
claun/core/communication/server/authenticators/file_authenticator.py
claun/core/communication/server/authenticators/void_authenticator.py
claun/modules/__init__.py
claun/modules/rstprocessor.py
claun/modules/screensaverpoc.py
claun/modules/applications/__init__.py
claun/modules/applications/model.py
claun/modules/applications/admin/__init__.py
claun/modules/applications/admin/model.py
claun/modules/applications/admin/help/__init__.py
claun/modules/applications/admin/help/application.html
claun/modules/applications/admin/help/application.json
claun/modules/apprunner/__init__.py
claun/modules/apprunner/frameworks/__init__.py
claun/modules/apprunner/frameworks/abstract_framework.py
claun/modules/apprunner/frameworks/cavelib.py
claun/modules/cluster/__init__.py
claun/modules/cluster/apprunnerclient.py
claun/modules/cluster/controllerclient.py
claun/modules/controller/__init__.py
claun/modules/controller/controllers/__init__.py
claun/modules/controller/controllers/abstract_controller.py
claun/modules/controller/controllers/trackd.py
claun/modules/couchdb/__init__.py
claun/modules/couchdb/wrapper.py
claun/modules/distribappcontrol/__init__.py
claun/modules/distribappcontrol/controllerconfiguration.py
claun/modules/distribappcontrol/controllers.py
claun/modules/distribappcontrol/frameworkconfiguration.py
