Metadata-Version: 1.0
Name: claun
Version: 2.0.0.6
Summary: Claun system for distributed environments
Home-page: example.com
Author: Jiri Chadima
Author-email: chadima.jiri@gmail.com
License: Other
Platform: UNKNOWN
Classifier: Development Status :: 3 - Alpha
Classifier: Intended Audience :: Developers
Classifier: Intended Audience :: Education
Classifier: License :: Other/Proprietary License
Classifier: Programming Language :: Python
Classifier: Topic :: System :: Distributed Computing
Classifier: Programming Language :: Python :: 2.6
Classifier: Programming Language :: Python :: 2.7
